Full Adder/full_adder.v
module full_adder (
    sum, carry, a, b, c
);
  input a, b, c;
  output sum, carry;

  assign sum = a ^ b ^ c;
  assign carry = (a & b) + (b & c) + (c & a);  
endmodule

Full Adder/full_adder_tb.v
module full_adder_tb;

 // Inputs
 reg a;
 reg b;
 reg c;

 // Outputs
 wire sum;
 wire carry;

 full_adder FA(
    .a(a), .b(b), .c(c), .sum(sum), .carry(carry)
 );

 initial begin
    $dumpfile("full_adder.vcd"); // dumpfile created
    $dumpvars(0, full_adder_tb);

    $monitor($time, " a = %b, b = %b, c = %b, sum = %b, carry = %b", a, b, c, sum, carry); // Print command

    a = 0; b = 0; c = 0; #5;
    a = 0; b = 0; c = 1; #5;
    a = 0; b = 1; c = 0; #5;
    a = 0; b = 1; c = 1; #5;
    a = 1; b = 0; c = 0; #5;
    a = 1; b = 0; c = 1; #5;
    a = 1; b = 1; c = 0; #5;
    a = 1; b = 1; c = 1; #5;
    $finish;
 end
endmodule

Full Adder/full_adder.vcd
$date
	Sun Jul 20 12:29:47 2025
$end
$version
	Icarus Verilog
$end
$timescale
	1s
$end
$scope module full_adder_tb $end
$var wire 1 ! sum $end
$var wire 1 " carry $end
$var reg 1 # a $end
$var reg 1 $ b $end
$var reg 1 % c $end
$scope module FA $end
$var wire 1 # a $end
$var wire 1 $ b $end
$var wire 1 % c $end
$var wire 1 ! sum $end
$var wire 1 " carry $end
$upscope $end
$upscope $end
$enddefinitions $end
$comment Show the parameter values. $end
$dumpall
$end
#0
$dumpvars
0%
0$
0#
0"
0!
$end
#5
1!
1%
#10
0%
1$
#15
0!
1"
1%
#20
1!
0"
0%
0$
1#
#25
0!
1"
1%
#30
1"
0%
1$
#35
1!
1"
1%
