Full Subtractor/full_subtractor.v
module full_subtractor (
    diff, borrow, a, b, c
);
    input a, b, c;
    output diff, borrow;

    assign diff = (a ^ b ^ c);
    assign borrow = (~a & c) + (~a & b) + (b & c);
endmodule

Full Subtractor/full_subtractor_tb.v
module full_subtractor_tb;

// Inputs 
reg a;
reg b;
reg c;

// Outputs
wire diff;
wire borrow;

full_subtractor FS(
    .a(a), .b(b), .c(c), .diff(diff), .borrow(borrow)
);

initial begin
    // Testbench
    $dumpfile("full_subtractor.vcd");
    $dumpvars(0, full_subtractor_tb);

    $monitor(($time), " a = %b, b = %b, c = %b | diff = %b | borrow = %b", a, b, c, diff, borrow);

    a = 0; b = 0; c = 0; #5;
    a = 0; b = 0; c = 1; #5;
    a = 0; b = 1; c = 0; #5;
    a = 0; b = 1; c = 1; #5;
    a = 1; b = 0; c = 0; #5;
    a = 1; b = 0; c = 1; #5;
    a = 1; b = 1; c = 0; #5;
    a = 1; b = 1; c = 1; #5;
    $finish;
end
endmodule

Full Subtractor/full_subtractor.vcd
$date
	Sun Jul 20 13:07:59 2025
$end
$version
	Icarus Verilog
$end
$timescale
	1s
$end
$scope module full_subtractor_tb $end
$var wire 1 ! diff $end
$var wire 1 " borrow $end
$var reg 1 # a $end
$var reg 1 $ b $end
$var reg 1 % c $end
$scope module FS $end
$var wire 1 # a $end
$var wire 1 $ b $end
$var wire 1 % c $end
$var wire 1 ! diff $end
$var wire 1 " borrow $end
$upscope $end
$upscope $end
$enddefinitions $end
$comment Show the parameter values. $end
$dumpall
$end
#0
$dumpvars
0%
0$
0#
0"
0!
$end
#5
1!
1"
1%
#10
1"
0%
1$
#15
0!
1"
1%
#20
1!
0"
0%
0$
1#
#25
0!
1%
#30
0%
1$
#35
1!
1"
1%
