SR - FF/sr_ff.v
module sr_ff (
    input wire clock,
    input wire S,
    input wire R,
    output reg Q = 0
);

    always @(posedge clock) begin
        case ({S, R})
            2'b00 : Q <= Q;  // Depicts no change
            2'b01 : Q <= 0;  // Depicts a reset
            2'b10 : Q <= 1;  // Depicts a set
            2'b11 : Q <= 1'bx;  // Depicts a invalid case
        endcase
    end
    
endmodule

SR - FF/sr_ff_tb.v
module sr_ff_tb;    

    // Inputs
    reg clock;
    reg S;
    reg R;

    // Outputs
    wire Q;

    sr_ff DUT(
        .clock(clock), .S(S), .R(R), .Q(Q)
    );

    initial begin
        clock = 0;
        forever #5 clock = ~clock;
    end

    initial begin
        $dumpfile("srff.vcd");
        $dumpvars(0, sr_ff_tb);

        // TestCase 1
        S = 0; R = 0; #10;  // No change
        $display($time, " S = %b | R = %b | Q = %b", S, R, Q);

        // TestCase 2
        S = 1; R = 0; #10;  // Set
        $display($time, " S = %b | R = %b | Q = %b", S, R, Q);

        // TestCase 3
        S = 0; R = 1; #10;  // Reset
        $display($time, " S = %b | R = %b | Q = %b", S, R, Q);

        // TestCase 4
        S = 0; R = 0; #10;  // No change
        $display($time, " S = %b | R = %b | Q = %b", S, R, Q);

        // TestCase 5
        S = 1; R = 1; #10;  // Invalid
        $display($time, " S = %b | R = %b | Q = %b", S, R, Q);

        $finish;
    end
endmodule

SR - FF/srff.vcd
$date
	Thu Jul 24 13:24:47 2025
$end
$version
	Icarus Verilog
$end
$timescale
	1s
$end
$scope module sr_ff_tb $end
$var wire 1 ! Q $end
$var reg 1 " R $end
$var reg 1 # S $end
$var reg 1 $ clock $end
$scope module DUT $end
$var wire 1 " R $end
$var wire 1 # S $end
$var wire 1 $ clock $end
$var reg 1 ! Q $end
$upscope $end
$upscope $end
$enddefinitions $end
$comment Show the parameter values. $end
$dumpall
$end
#0
$dumpvars
0$
0#
0"
0!
$end
#5
1$
#10
0$
1#
#15
1!
1$
#20
0$
1"
0#
#25
0!
1$
#30
0$
0"
#35
1$
#40
0$
1"
1#
#45
x!
1$
