DEMUX/1X8/demux1to8.v
module demux1to8 (
    input wire in,
    input[2:0] sel,
    output reg[7:0] out
);

    always @(*) begin
        out = 8'b00000000;
        case (sel)
            3'b000: out[0] = in;
            3'b001: out[1] = in;
            3'b010: out[2] = in;
            3'b011: out[3] = in;
            3'b100: out[4] = in;
            3'b101: out[5] = in;
            3'b110: out[6] = in;
            3'b111: out[7] = in;
        endcase
    end
    
endmodule

DEMUX/1X8/demux1to8_tb.v
module demux1to8_tb;
    //Input
    reg in;
    reg[2:0] sel;

    // Outputs
    wire[7 : 0] out;

    demux1to8 DUT(
        .in(in), .sel(sel), .out(out)
    );

    initial begin
        $dumpfile("demux8bit.vcd");
        $dumpvars(0, demux1to8_tb);
        $monitor($time, " in = %b | sel = %b | out = %b", in, sel, out);
    end

    initial begin
        in = 1; #10;
        sel = 3'b000 ; #10;
        sel = 3'b001 ; #10;
        sel = 3'b010 ; #10;
        sel = 3'b011 ; #10;
        sel = 3'b100 ; #10;
        sel = 3'b101 ; #10;
        sel = 3'b110 ; #10;
        sel = 3'b111 ; #10;
        $finish;
    end
endmodule

DEMUX/1X8/demux8bit.vcd
$date
	Mon Jul 21 17:44:51 2025
$end
$version
	Icarus Verilog
$end
$timescale
	1s
$end
$scope module demux1to8_tb $end
$var wire 8 ! out [7:0] $end
$var reg 1 " in $end
$var reg 3 # sel [2:0] $end
$scope module DUT $end
$var wire 1 " in $end
$var wire 3 $ sel [2:0] $end
$var reg 8 % out [7:0] $end
$upscope $end
$upscope $end
$enddefinitions $end
$comment Show the parameter values. $end
$dumpall
$end
#0
$dumpvars
b0 %
bx $
bx #
1"
b0 !
$end
#10
b1 !
b1 %
b0 #
b0 $
#20
b10 !
b10 %
b1 #
b1 $
#30
b100 !
b100 %
b10 #
b10 $
#40
b1000 !
b1000 %
b11 #
b11 $
#50
b10000 !
b10000 %
b100 #
b100 $
#60
b100000 !
b100000 %
b101 #
b101 $
#70
b1000000 !
b1000000 %
b110 #
b110 $
#80
b10000000 !
b10000000 %
b111 #
b111 $
