Counters/UpDown Counter/counter_up_down.v
module counter_up_down (
    input wire clock,
    input wire reset,
    input wire mode,
    output reg[3:0] count
);

    always @(posedge clock or posedge reset) begin
        if(reset) count <= 4'b0000;
        else if(mode) count <= count + 1;
        else count <= count - 1;
    end 
    
endmodule

Counters/UpDown Counter/counter_up_down_tb.v
module counter_up_down_tb;

    // Input
    reg clock;
    reg reset;
    reg mode;

    // Output
    wire[3:0] count;
    

    counter_up_down DUT (
        .clock(clock), .reset(reset), .mode(mode), .count(count)
    );

    always #5 clock = ~clock;

    initial begin
        reset = 1;
        clock = 0;
        mode = 1;
        #10;

        reset = 0;

        #100;

        mode = 0;

        #100;
        $finish;
    end

    initial begin
        $dumpfile("updowncounter.vcd");
        $dumpvars(0, counter_up_down_tb);
        $monitor($time," Reset = %b | Mode = %b | Count = %b", reset, mode, count);
    end
endmodule

Counters/UpDown Counter/updowncounter.vcd
$date
	Sun Jul 27 13:29:59 2025
$end
$version
	Icarus Verilog
$end
$timescale
	1s
$end
$scope module counter_up_down_tb $end
$var wire 4 ! count [3:0] $end
$var reg 1 " clock $end
$var reg 1 # mode $end
$var reg 1 $ reset $end
$scope module DUT $end
$var wire 1 " clock $end
$var wire 1 # mode $end
$var wire 1 $ reset $end
$var reg 4 % count [3:0] $end
$upscope $end
$upscope $end
$enddefinitions $end
$comment Show the parameter values. $end
$dumpall
$end
#0
$dumpvars
b0 %
1$
1#
0"
b0 !
$end
#5
1"
#10
0"
0$
#15
b1 !
b1 %
1"
#20
0"
#25
b10 !
b10 %
1"
#30
0"
#35
b11 !
b11 %
1"
#40
0"
#45
b100 !
b100 %
1"
#50
0"
#55
b101 !
b101 %
1"
#60
0"
#65
b110 !
b110 %
1"
#70
0"
#75
b111 !
b111 %
1"
#80
0"
#85
b1000 !
b1000 %
1"
#90
0"
#95
b1001 !
b1001 %
1"
#100
0"
#105
b1010 !
b1010 %
1"
#110
0"
0#
#115
b1001 !
b1001 %
1"
#120
0"
#125
b1000 !
b1000 %
1"
#130
0"
#135
b111 !
b111 %
1"
#140
0"
#145
b110 !
b110 %
1"
#150
0"
#155
b101 !
b101 %
1"
#160
0"
#165
b100 !
b100 %
1"
#170
0"
#175
b11 !
b11 %
1"
#180
0"
#185
b10 !
b10 %
1"
#190
0"
#195
b1 !
b1 %
1"
#200
0"
#205
b0 !
b0 %
1"
