MUX/8X1/mux8to1.v
module mux8to1 (
    input wire [7:0] in, // input lines
    input wire [2:0] sel, // select lines
    output wire y  // output line
);
    // Selecting input based on the value
    assign y = (sel == 3'b000) ? in[0] : 
               (sel == 3'b001) ? in[1] :
               (sel == 3'b010) ? in[2] :
               (sel == 3'b011) ? in[3] :
               (sel == 3'b100) ? in[4] :
               (sel == 3'b101) ? in[5] :
               (sel == 3'b110) ? in[6] :
                                 in[7];
endmodule

MUX/8X1/mux8to1_tb.v
module mux8to1_tb;
//Input
reg[7:0] in;
reg[2:0] sel;

//Output
wire y;

mux8to1 DUT(
    .in(in), .sel(sel), .y(y)
);

initial begin
    $dumpfile("mux8bit.vcd");
    $dumpvars(0, mux8to1_tb);
    $monitor($time, " sel = %d, y = %b", sel, y);
end

initial begin
    // Test case 
    in = 8'b10101010;
    sel = 3'b000;
    repeat(7) begin
        #10;
        sel = sel + 1;
    end
    #10;
    $finish;
end


endmodule

MUX/8X1/mux8bit.vcd
$date
	Mon Jul 21 14:19:36 2025
$end
$version
	Icarus Verilog
$end
$timescale
	1s
$end
$scope module mux8to1_tb $end
$var wire 1 ! y $end
$var reg 8 " in [7:0] $end
$var reg 3 # sel [2:0] $end
$scope module DUT $end
$var wire 8 $ in [7:0] $end
$var wire 3 % sel [2:0] $end
$var wire 1 ! y $end
$upscope $end
$upscope $end
$enddefinitions $end
$comment Show the parameter values. $end
$dumpall
$end
#0
$dumpvars
b0 %
b10101010 $
b0 #
b10101010 "
0!
$end
#10
1!
b1 #
b1 %
#20
0!
b10 #
b10 %
#30
1!
b11 #
b11 %
#40
0!
b100 #
b100 %
#50
1!
b101 #
b101 %
#60
0!
b110 #
b110 %
#70
1!
b111 #
b111 %
