Counters/Down Counter/counter_down.v
module counter_down (
    input wire clock,
    input wire reset,
    output reg[3:0] count 
);

    always @(posedge clock or posedge reset) begin
        if(count == 0)
            count <= 4'b1111;
        else if(reset) 
            count <= 4'b1111;
        else
            count <= count - 1;    
    end
    
endmodule

Counters/Down Counter/counter_down_tb.v
module counter_down_tb;

    // Inputs
    reg clock;
    reg reset;

    // Output
    wire[3:0] count;

    counter_down DUT(
        .clock(clock), .reset(reset), .count(count)
    );

    always #5 clock = ~clock;


    initial begin
        reset = 1;
        clock = 0;
        #10;

        reset = 0;

        #200;

        $finish;
    end

    initial begin
        $dumpfile("downcounter4bit.vcd");
        $dumpvars(0, counter_down_tb);
        $monitor($time, " Reset = %b | Count = %b", reset, count);
    end
endmodule

Counters/Down Counter/downcounter4bit.vcd
$date
	Sun Jul 27 12:59:51 2025
$end
$version
	Icarus Verilog
$end
$timescale
	1s
$end
$scope module counter_down_tb $end
$var wire 4 ! count [3:0] $end
$var reg 1 " clock $end
$var reg 1 # reset $end
$scope module DUT $end
$var wire 1 " clock $end
$var wire 1 # reset $end
$var reg 4 $ count [3:0] $end
$upscope $end
$upscope $end
$enddefinitions $end
$comment Show the parameter values. $end
$dumpall
$end
#0
$dumpvars
b1111 $
1#
0"
b1111 !
$end
#5
1"
#10
0"
0#
#15
b1110 !
b1110 $
1"
#20
0"
#25
b1101 !
b1101 $
1"
#30
0"
#35
b1100 !
b1100 $
1"
#40
0"
#45
b1011 !
b1011 $
1"
#50
0"
#55
b1010 !
b1010 $
1"
#60
0"
#65
b1001 !
b1001 $
1"
#70
0"
#75
b1000 !
b1000 $
1"
#80
0"
#85
b111 !
b111 $
1"
#90
0"
#95
b110 !
b110 $
1"
#100
0"
#105
b101 !
b101 $
1"
#110
0"
#115
b100 !
b100 $
1"
#120
0"
#125
b11 !
b11 $
1"
#130
0"
#135
b10 !
b10 $
1"
#140
0"
#145
b1 !
b1 $
1"
#150
0"
#155
b0 !
b0 $
1"
#160
0"
#165
b1111 !
b1111 $
1"
#170
0"
#175
b1110 !
b1110 $
1"
#180
0"
#185
b1101 !
b1101 $
1"
#190
0"
#195
b1100 !
b1100 $
1"
#200
0"
#205
b1011 !
b1011 $
1"
