MUX/4X1/mux4to1.v
module mux4to1 (
    input i0, i1, i2, i3,
    input[1:0] sel,
    output y
);
  assign y = (sel == 2'b00) ? i0 :
             (sel == 2'b01) ? i1 :
             (sel == 2'b10) ? i2 :
             i3;
endmodule

MUX/4X1/mux4to1_tb.v
module mux4to1_tb;
// Inputs
reg i0, i1, i2, i3;
reg[1:0] sel;

// Outputs
wire y;

mux4to1 DUT(
    .i0(i0), .i1(i1), .i2(i2), .i3(i3), .sel(sel), .y(y)
);

initial begin
    $dumpfile("mux4bit.vcd");
    $dumpvars(0, mux4to1_tb);

    $monitor($time, " i0 = %b, i1 = %b, i2 = %b, i3 = %b, sel = %b | y = %b", i0, i1, i2, i3, sel, y);

    i0 = 0; i1 = 1; i2 = 0; i3 = 1;
    sel = 2'b00; #10;
    sel = 2'b01; #10;
    sel = 2'b10; #10;
    sel = 2'b11; #10;

    i0 = 1; i1 = 0; i2 = 1; i3 = 0;
    sel = 2'b00; #10;
    sel = 2'b01; #10;
    sel = 2'b10; #10;
    sel = 2'b11; #10;


    i0 = 1; i1 = 0; i2 = 0; i3 = 1;
    sel = 2'b00; #10;
    sel = 2'b01; #10;
    sel = 2'b10; #10;
    sel = 2'b11; #10;
end

endmodule

MUX/4X1/mux4bit.vcd
$date
	Sun Jul 20 23:03:01 2025
$end
$version
	Icarus Verilog
$end
$timescale
	1s
$end
$scope module mux4to1_tb $end
$var wire 1 ! y $end
$var reg 1 " i0 $end
$var reg 1 # i1 $end
$var reg 1 $ i2 $end
$var reg 1 % i3 $end
$var reg 2 & sel [1:0] $end
$scope module DUT $end
$var wire 1 " i0 $end
$var wire 1 # i1 $end
$var wire 1 $ i2 $end
$var wire 1 % i3 $end
$var wire 2 ' sel [1:0] $end
$var wire 1 ! y $end
$upscope $end
$upscope $end
$enddefinitions $end
$comment Show the parameter values. $end
$dumpall
$end
#0
$dumpvars
b0 '
b0 &
1%
0$
1#
0"
0!
$end
#10
1!
b1 &
b1 '
#20
0!
b10 &
b10 '
#30
1!
b11 &
b11 '
#40
b0 &
b0 '
0%
1$
0#
1"
#50
0!
b1 &
b1 '
#60
1!
b10 &
b10 '
#70
0!
b11 &
b11 '
#80
1!
b0 &
b0 '
1%
0$
#90
0!
b1 &
b1 '
#100
b10 &
b10 '
#110
1!
b11 &
b11 '
