Counters/Up Counter/counter_up.v
module counter_up (
    input wire clock,
    input wire reset,
    output reg [3:0] count
);
    always @(posedge clock or posedge reset) begin
        if (reset)
            count = 4'b0000;
        else
            count = count + 1;
    end
endmodule

Counters/Up Counter/counter_up_tb.v
module counter_up_tb;

    // Inputs
    reg clock;
    reg reset;

    // Output
    wire[3:0] count;

    counter_up DUT(
        .clock(clock), .reset(reset), .count(count)
    );

    always #5 clock = ~clock;

    initial begin
        clock = 0;
        reset = 1;
        #10;
        reset = 0;
        #160;
        $finish;
    end


    initial begin
        $dumpfile("upcounter4bit.vcd");
        $dumpvars(0, counter_up_tb);
        $monitor($time, " Reset = %b | Count = %b", reset,count);
    end
endmodule

Counters/Up Counter/upcounter4bit.vcd
$date
	Sun Jul 27 12:27:44 2025
$end
$version
	Icarus Verilog
$end
$timescale
	1s
$end
$scope module counter_up_tb $end
$var wire 4 ! count [3:0] $end
$var reg 1 " clock $end
$var reg 1 # reset $end
$scope module DUT $end
$var wire 1 " clock $end
$var wire 1 # reset $end
$var reg 4 $ count [3:0] $end
$upscope $end
$upscope $end
$enddefinitions $end
$comment Show the parameter values. $end
$dumpall
$end
#0
$dumpvars
b0 $
1#
0"
b0 !
$end
#5
1"
#10
0"
0#
#15
b1 !
b1 $
1"
#20
0"
#25
b10 !
b10 $
1"
#30
0"
#35
b11 !
b11 $
1"
#40
0"
#45
b100 !
b100 $
1"
#50
0"
#55
b101 !
b101 $
1"
#60
0"
#65
b110 !
b110 $
1"
#70
0"
#75
b111 !
b111 $
1"
#80
0"
#85
b1000 !
b1000 $
1"
#90
0"
#95
b1001 !
b1001 $
1"
#100
0"
#105
b1010 !
b1010 $
1"
#110
0"
#115
b1011 !
b1011 $
1"
#120
0"
#125
b1100 !
b1100 $
1"
#130
0"
#135
b1101 !
b1101 $
1"
#140
0"
#145
b1110 !
b1110 $
1"
#150
0"
#155
b1111 !
b1111 $
1"
#160
0"
#165
b0 !
b0 $
1"
#170
0"
#175
b1 !
b1 $
1"
#180
0"
#185
b10 !
b10 $
1"
#190
0"
#195
b11 !
b11 $
1"
#200
0"
#205
b100 !
b100 $
1"
#210
0"
#215
b101 !
b101 $
1"
#220
0"
#225
b110 !
b110 $
1"
#230
0"
#235
b111 !
b111 $
1"
#240
0"
#245
b1000 !
b1000 $
1"
#250
0"
#255
b1001 !
b1001 $
1"
#260
0"
#265
b1010 !
b1010 $
1"
#270
0"
#275
b1011 !
b1011 $
1"
#280
0"
#285
b1100 !
b1100 $
1"
#290
0"
#295
b1101 !
b1101 $
1"
#300
0"
#305
b1110 !
b1110 $
1"
